visea/README.md
visea/__init__.py
visea/analyze.py
visea/assoc.py
visea/cli.py
visea/plots.py
visea/py.typed
visea/report.py
visea/stats.py
visea/text.py
visea/typing.py
visea-0.1.0.dist-info/METADATA
visea-0.1.0.dist-info/WHEEL
visea-0.1.0.dist-info/entry_points.txt
visea-0.1.0.dist-info/licenses/LICENSE
visea-0.1.0.dist-info/RECORD
